kafka_transport/__init__.py
kafka_transport/__main__.py
kafka_transport/errors.py
kafka_transport/listener.py
kafka_transport/requester.py
kafka_transport/tests/TestListener.py
kafka_transport/tests/__init__.py
kafka_transport-0.7.6.dist-info/METADATA
kafka_transport-0.7.6.dist-info/WHEEL
kafka_transport-0.7.6.dist-info/top_level.txt
kafka_transport-0.7.6.dist-info/RECORD
