Metadata-Version: 2.1
Name: kafka-transport
Version: 0.7.6
Summary: UNKNOWN
Home-page: https://github.com/Karma-blockchain/kafka-transport
Author: Nozdrin-Plotnitsky Nikolay
Author-email: nozdrin.plotnitsky@karma.red
License: MIT
Platform: UNKNOWN
Requires-Dist: msgpack (<1.1.0,>=1.0.0)
Requires-Dist: kafka-python (<2.1.0,>=2.0.1)
